poetry_plugin_hook/__init__.py
poetry_plugin_hook/bump.py
poetry_plugin_hook/latest.py
poetry_plugin_hook/redirect.py
poetry_plugin_hook/sync.py
poetry_plugin_hook-1.4.0.dist-info/LICENSE
poetry_plugin_hook-1.4.0.dist-info/METADATA
poetry_plugin_hook-1.4.0.dist-info/WHEEL
poetry_plugin_hook-1.4.0.dist-info/entry_points.txt
poetry_plugin_hook-1.4.0.dist-info/RECORD
