Metadata-Version: 2.3
Name: poetry-plugin-hook
Version: 1.4.0
Summary: poetry plugin to register wrapped commands to use as pre-commit-hooks
License: MIT
Keywords: poetry,pre-commit,plugin,hook
Author: Christoph Dörrer
Author-email: d-chris@web.de
Requires-Python: >=3.9,<4.0
Classifier: License :: OSI Approved :: MIT License
Classifier: Operating System :: OS Independent
Classifier: Programming Language :: Python :: 3
Classifier: Programming Language :: Python :: 3.9
Classifier: Programming Language :: Python :: 3.10
Classifier: Programming Language :: Python :: 3.11
Classifier: Programming Language :: Python :: 3.12
Classifier: Programming Language :: Python :: 3.13
Classifier: Topic :: Software Development :: Build Tools
Classifier: Topic :: Software Development :: Libraries :: Python Modules
Requires-Dist: cleo (>=2.1.0,<3.0.0)
Requires-Dist: poetry (>=1.7.0)
Project-URL: documentation, https://d-chris.github.io/poetry-plugin-hook
Project-URL: repository, https://github.com/d-chris/poetry-plugin-hook
